fubam/__init__.py
fubam/fubam.py
fubam/optHelper.py
fubam-0.1.0.dist-info/licenses/licenses/LICENSE - cssmin
fubam-0.1.0.dist-info/licenses/licenses/LICENSE - fubam
fubam-0.1.0.dist-info/licenses/licenses/LICENSE - rjsmin
fubam-0.1.0.dist-info/METADATA
fubam-0.1.0.dist-info/WHEEL
fubam-0.1.0.dist-info/top_level.txt
fubam-0.1.0.dist-info/RECORD
