Metadata-Version: 2.4
Name: fubam
Version: 0.1.0
Summary: A Python-based HTML builder with built-in SEO, accessibility, layout injection, and optional minification.
Author-email: Aman Ali <chad.aman.ali@gmail.com>
License-Expression: MIT
Project-URL: Homepage, https://github.com/amanalimon/fubam
Project-URL: Repository, https://github.com/amanalimon/fubam
Requires-Python: >=3.7
License-File: licenses/LICENSE - cssmin
License-File: licenses/LICENSE - fubam
License-File: licenses/LICENSE - rjsmin
Dynamic: license-file
